api/__init__.py
api/handlers/__init__.py
api/handlers/__static__.py
api/handlers/async_conn/__init__.py
api/handlers/async_conn/base_handler.py
api/handlers/async_conn/consume_handler.py
api/handlers/async_conn/publish_handler.py
api/handlers/sync_conn/__init__.py
api/handlers/sync_conn/base_handler.py
api/handlers/sync_conn/read_handler.py
api/handlers/sync_conn/write_handler.py
async_rabbit_mq/__init__.py
async_rabbit_mq/consumer.py
async_rabbit_mq/publisher.py
config/__init__.py
config/config.py
config/logger.py
sync_rabbit_mq/__init__.py
sync_rabbit_mq/dataclasses.py
sync_rabbit_mq/messages/__init__.py
sync_rabbit_mq/messages/listen.py
sync_rabbit_mq/messages/write.py
smbh_rabbit_mq_wrapper-0.0.0.1.dist-info/METADATA
smbh_rabbit_mq_wrapper-0.0.0.1.dist-info/WHEEL
smbh_rabbit_mq_wrapper-0.0.0.1.dist-info/top_level.txt
smbh_rabbit_mq_wrapper-0.0.0.1.dist-info/RECORD
