Metadata-Version: 2.1
Name: smbh-rabbit-mq-wrapper
Version: 0.0.0.1
Summary: RabbitMQ Wrapper for solve some tasks
Home-page: https://github.com/SMEDIA-BUYING-HOLDING/RabbitMQWrapper
Author: Alexander Vino
Author-email: alexander-vin0@yandex.ru
License: UNKNOWN
Platform: UNKNOWN
Requires-Python: >=3.10
